[][{"brandId":1978,"brandName":"阿迪达斯","multiChoose":true,"shortName":"阿迪达斯"},{"brandId":2118,"brandName":"耐克","multiChoose":true,"shortName":"耐克"},{"brandId":14553,"brandName":"李宁","multiChoose":true,"shortName":"李宁"},{"brandId":3334,"brandName":"彪马","multiChoose":true,"shortName":"彪马"},{"brandId":2273,"brandName":"new balance","multiChoose":true,"shortName":"new balance"},{"brandId":3338,"brandName":"安德玛","multiChoose":true,"shortName":"安德玛"},{"brandId":3722,"brandName":"美津浓","multiChoose":true,"shortName":"美津浓"},{"brandId":6836,"brandName":"umbro 茵宝","multiChoose":true,"shortName":"umbro 茵宝"},{"brandId":3966,"brandName":"斯凯奇","multiChoose":true,"shortName":"斯凯奇"},{"brandId":1303,"brandName":"之宝","multiChoose":true,"shortName":"之宝"},{"brandId":12119,"brandName":"Kappa","multiChoose":true,"shortName":"Kappa"},{"brandId":7020,"brandName":"AIGLE ","multiChoose":true,"shortName":"AIGLE "},{"brandId":2201,"brandName":"亚瑟士","multiChoose":true,"shortName":"亚瑟士"},{"brandId":3353,"brandName":"范斯","multiChoose":true,"shortName":"范斯"},{"brandId":10483,"brandName":"暴走的萝莉","multiChoose":true,"shortName":"暴走的萝莉"},{"brandId":2357,"brandName":"匡威","multiChoose":true,"shortName":"匡威"},{"brandId":3713,"brandName":"哥伦比亚","multiChoose":true,"shortName":"哥伦比亚"},{"brandId":3352,"brandName":"添柏岚","multiChoose":true,"shortName":"添柏岚"},{"brandId":17000,"brandName":"Lafuma 乐飞叶","multiChoose":true,"shortName":"Lafuma 乐飞叶"},{"brandId":5538,"brandName":"始祖鸟","multiChoose":true,"shortName":"始祖鸟"},{"brandId":4565,"brandName":"Mammut","multiChoose":true,"shortName":"Mammut"},{"brandId":4052,"brandName":"鬼冢虎","multiChoose":true,"shortName":"鬼冢虎"},{"brandId":6419,"brandName":"速比涛","multiChoose":true,"shortName":"速比涛"},{"brandId":1412,"brandName":"凯浦林","multiChoose":true,"shortName":"凯浦林"},{"brandId":3102,"brandName":"锐步","multiChoose":true,"shortName":"锐步"},{"brandId":14429,"brandName":"Mitchell & Ness","multiChoose":true,"shortName":"Mitchell & Ness"},{"brandId":2274,"brandName":"TITIKA","multiChoose":true,"shortName":"TITIKA"},{"brandId":2508,"brandName":"乐斯菲斯","multiChoose":true,"shortName":"乐斯菲斯"},{"brandId":13726,"brandName":"安踏","multiChoose":true,"shortName":"安踏"},{"brandId":13080,"brandName":"NBA","multiChoose":true,"shortName":"NBA"},{"brandId":6418,"brandName":"YONEX 尤尼克斯","multiChoose":true,"shortName":"YONEX 尤尼克斯"},{"brandId":6960,"brandName":"诺诗兰","multiChoose":true,"shortName":"诺诗兰"},{"brandId":5583,"brandName":"粒子狂热","multiChoose":true,"shortName":"粒子狂热"},{"brandId":6935,"brandName":"arena","multiChoose":true,"shortName":"arena"},{"brandId":4180,"brandName":"Air jordan","multiChoose":true,"shortName":"Air jordan"},{"brandId":1749,"brandName":"HOTSUIT","multiChoose":true,"shortName":"HOTSUIT"},{"brandId":4282,"brandName":"patagonia","multiChoose":true,"shortName":"patagonia"},{"brandId":2457,"brandName":"DCSHOECOUSA","multiChoose":true,"shortName":"DCSHOECOUSA"},{"brandId":6875,"brandName":"卡蒙","multiChoose":true,"shortName":"卡蒙"},{"brandId":3698,"brandName":"Dr.Martens","multiChoose":true,"shortName":"Dr.Martens"},{"brandId":12539,"brandName":"HATSON","multiChoose":true,"shortName":"HATSON"},{"brandId":9985,"brandName":"范德安","multiChoose":true,"shortName":"范德安"},{"brandId":13986,"brandName":"布来亚克","multiChoose":true,"shortName":"布来亚克"},{"brandId":2538,"brandName":"网易严选","multiChoose":true,"shortName":"网易严选"},{"brandId":4267,"brandName":"OZWEAR","multiChoose":true,"shortName":"OZWEAR"},{"brandId":1992,"brandName":"Jansport","multiChoose":true,"shortName":"Jansport"},{"brandId":3546,"brandName":"洛娜珍","multiChoose":true,"shortName":"洛娜珍"},{"brandId":3915,"brandName":"土拨鼠","multiChoose":true,"shortName":"土拨鼠"},{"brandId":5411,"brandName":"萨洛蒙","multiChoose":true,"shortName":"萨洛蒙"},{"brandId":6924,"brandName":"5.11","multiChoose":true,"shortName":"5.11"},{"brandId":4078,"brandName":"黑钻","multiChoose":true,"shortName":"黑钻"},{"brandId":17765,"brandName":"凯乐石","multiChoose":true,"shortName":"凯乐石"},{"brandId":5129,"brandName":"Rakuten","multiChoose":true,"shortName":"Rakuten"},{"brandId":7039,"brandName":"斐乐","multiChoose":true,"shortName":"斐乐"},{"brandId":4814,"brandName":"Manduka","multiChoose":true,"shortName":"Manduka"},{"brandId":2440,"brandName":"Let's diet","multiChoose":true,"shortName":"Let's diet"},{"brandId":1433,"brandName":"Herschel Supply","multiChoose":true,"shortName":"Herschel Supply"},{"brandId":5605,"brandName":"Everugg","multiChoose":true,"shortName":"Everugg"},{"brandId":4424,"brandName":"Keds","multiChoose":true,"shortName":"Keds"},{"brandId":9023,"brandName":"DK Sheepskin","multiChoose":true,"shortName":"DK Sheepskin"},{"brandId":8245,"brandName":"2XU","multiChoose":true,"shortName":"2XU"},{"brandId":1974,"brandName":"Fjällräven 北极狐","multiChoose":true,"shortName":"Fjällräven 北极狐"},{"brandId":4075,"brandName":"LOWA","multiChoose":true,"shortName":"LOWA"},{"brandId":2327,"brandName":"维氏","multiChoose":true,"shortName":"维氏"},{"brandId":5467,"brandName":"奥递乐","multiChoose":true,"shortName":"奥递乐"},{"brandId":8001,"brandName":"CLAW MONEY","multiChoose":true,"shortName":"CLAW MONEY"},{"brandId":3971,"brandName":"KEEN","multiChoose":true,"shortName":"KEEN"},{"brandId":3250,"brandName":"MAXWIN GYM","multiChoose":true,"shortName":"MAXWIN GYM"},{"brandId":4580,"brandName":"TIMBUK2","multiChoose":true,"shortName":"TIMBUK2"},{"brandId":4081,"brandName":"OUTDOOR RESEARCH","multiChoose":true,"shortName":"OUTDOOR RESEARCH"},{"brandId":3349,"brandName":"法国公鸡","multiChoose":true,"shortName":"法国公鸡"},{"brandId":1507,"brandName":"迷你唐卡","multiChoose":true,"shortName":"迷你唐卡"},{"brandId":7901,"brandName":"沙芬","multiChoose":true,"shortName":"沙芬"},{"brandId":4234,"brandName":"OSPREY","multiChoose":true,"shortName":"OSPREY"},{"brandId":5156,"brandName":"速尔","multiChoose":true,"shortName":"速尔"},{"brandId":17649,"brandName":"aim'n","multiChoose":true,"shortName":"aim'n"},{"brandId":6867,"brandName":"Asics Tiger 亚瑟士 虎","multiChoose":true,"shortName":"Asics Tiger 亚瑟士 虎"},{"brandId":3972,"brandName":"格里高利","multiChoose":true,"shortName":"格里高利"},{"brandId":7034,"brandName":"BABOLAT 百宝力","multiChoose":true,"shortName":"BABOLAT 百宝力"},{"brandId":4593,"brandName":"Champion","multiChoose":true,"shortName":"Champion"},{"brandId":1799,"brandName":"3M","multiChoose":true,"shortName":"3M"},{"brandId":3969,"brandName":"百福","multiChoose":true,"shortName":"百福"},{"brandId":14439,"brandName":"Quay Australia","multiChoose":true,"shortName":"Quay Australia"},{"brandId":2107,"brandName":"佳明","multiChoose":true,"shortName":"佳明"},{"brandId":8061,"brandName":"Tabio","multiChoose":true,"shortName":"Tabio"},{"brandId":13719,"brandName":"ASSC","multiChoose":true,"shortName":"ASSC"},{"brandId":16080,"brandName":"Ubras","multiChoose":true,"shortName":"Ubras"},{"brandId":7822,"brandName":"FITFLOP","multiChoose":true,"shortName":"FITFLOP"},{"brandId":9620,"brandName":"Atlantic STARS","multiChoose":true,"shortName":"Atlantic STARS"},{"brandId":995,"brandName":"飞利浦","multiChoose":true,"shortName":"飞利浦"},{"brandId":15097,"brandName":"PORSCHE DESIGN","multiChoose":true,"shortName":"PORSCHE DESIGN"},{"brandId":4612,"brandName":"777","multiChoose":true,"shortName":"777"},{"brandId":5314,"brandName":"布鲁克斯","multiChoose":true,"shortName":"布鲁克斯"},{"brandId":6137,"brandName":"SEA TO SUMMIT","multiChoose":true,"shortName":"SEA TO SUMMIT"},{"brandId":2546,"brandName":"简帛","multiChoose":true,"shortName":"简帛"},{"brandId":8739,"brandName":"ESGUARD","multiChoose":true,"shortName":"ESGUARD"},{"brandId":15440,"brandName":"LEXON","multiChoose":true,"shortName":"LEXON"},{"brandId":8100,"brandName":"Bestway","multiChoose":true,"shortName":"Bestway"},{"brandId":5620,"brandName":"逸客","multiChoose":true,"shortName":"逸客"},{"brandId":8023,"brandName":"宜视宝","multiChoose":true,"shortName":"宜视宝"},{"brandId":3335,"brandName":"其乐","multiChoose":true,"shortName":"其乐"},{"brandId":17652,"brandName":"Daquini","multiChoose":true,"shortName":"Daquini"},{"brandId":6933,"brandName":"COOLMAX","multiChoose":true,"shortName":"COOLMAX"},{"brandId":9879,"brandName":"神秘牧场","multiChoose":true,"shortName":"神秘牧场"},{"brandId":4076,"brandName":"洽洽鸟","multiChoose":true,"shortName":"洽洽鸟"},{"brandId":8095,"brandName":"LP","multiChoose":true,"shortName":"LP"},{"brandId":5917,"brandName":"华歌尔","multiChoose":true,"shortName":"华歌尔"},{"brandId":3326,"brandName":"驼峰","multiChoose":true,"shortName":"驼峰"},{"brandId":4080,"brandName":"威斯","multiChoose":true,"shortName":"威斯"},{"brandId":14847,"brandName":"VVC","multiChoose":true,"shortName":"VVC"},{"brandId":17658,"brandName":"Lilybod","multiChoose":true,"shortName":"Lilybod"},{"brandId":5086,"brandName":"多特","multiChoose":true,"shortName":"多特"},{"brandId":7801,"brandName":"后益","multiChoose":true,"shortName":"后益"},{"brandId":11044,"brandName":"Helinox","multiChoose":true,"shortName":"Helinox"},{"brandId":11220,"brandName":"Maxfever","multiChoose":true,"shortName":"Maxfever"},{"brandId":4745,"brandName":"欧克利","multiChoose":true,"shortName":"欧克利"},{"brandId":4796,"brandName":"Craft","multiChoose":true,"shortName":"Craft"},{"brandId":5961,"brandName":"KKtP","multiChoose":true,"shortName":"KKtP"},{"brandId":15659,"brandName":"YPL","multiChoose":true,"shortName":"YPL"},{"brandId":4082,"brandName":"NATHAN","multiChoose":true,"shortName":"NATHAN"},{"brandId":3746,"brandName":"Roxy","multiChoose":true,"shortName":"Roxy"},{"brandId":4232,"brandName":"狼爪","multiChoose":true,"shortName":"狼爪"},{"brandId":4828,"brandName":"勃肯","multiChoose":true,"shortName":"勃肯"},{"brandId":7188,"brandName":"Alpha Industries","multiChoose":true,"shortName":"Alpha Industries"},{"brandId":8932,"brandName":"易伽猫","multiChoose":true,"shortName":"易伽猫"},{"brandId":13219,"brandName":"BARREL","multiChoose":true,"shortName":"BARREL"},{"brandId":3944,"brandName":"卡特","multiChoose":true,"shortName":"卡特"},{"brandId":3960,"brandName":"TOMS","multiChoose":true,"shortName":"TOMS"},{"brandId":10079,"brandName":"飞比特","multiChoose":true,"shortName":"飞比特"},{"brandId":10299,"brandName":"猎鹰突起","multiChoose":true,"shortName":"猎鹰突起"},{"brandId":10810,"brandName":"Sunnybates","multiChoose":true,"shortName":"Sunnybates"},{"brandId":15163,"brandName":"MOC PAPA","multiChoose":true,"shortName":"MOC PAPA"},{"brandId":3970,"brandName":"优地","multiChoose":true,"shortName":"优地"},{"brandId":8027,"brandName":"奈爱","multiChoose":true,"shortName":"奈爱"},{"brandId":4253,"brandName":"蕉下","multiChoose":true,"shortName":"蕉下"},{"brandId":9098,"brandName":"Perla Ricci","multiChoose":true,"shortName":"Perla Ricci"},{"brandId":12659,"brandName":"TT7","multiChoose":true,"shortName":"TT7"},{"brandId":14286,"brandName":"karrimor","multiChoose":true,"shortName":"karrimor"},{"brandId":3932,"brandName":"SKORA","multiChoose":true,"shortName":"SKORA"},{"brandId":14645,"brandName":"VANCIVIL","multiChoose":true,"shortName":"VANCIVIL"},{"brandId":2106,"brandName":"颂拓","multiChoose":true,"shortName":"颂拓"},{"brandId":2407,"brandName":"威戈","multiChoose":true,"shortName":"威戈"},{"brandId":3736,"brandName":"澳大利亚EMU","multiChoose":true,"shortName":"澳大利亚EMU"},{"brandId":6126,"brandName":"EuroSCHIRM","multiChoose":true,"shortName":"EuroSCHIRM"},{"brandId":8022,"brandName":"视得乐","multiChoose":true,"shortName":"视得乐"},{"brandId":8539,"brandName":"JUSTFEEL","multiChoose":true,"shortName":"JUSTFEEL"},{"brandId":9206,"brandName":"PATRICK","multiChoose":true,"shortName":"PATRICK"},{"brandId":11043,"brandName":"Finetrack","multiChoose":true,"shortName":"Finetrack"},{"brandId":9685,"brandName":"欧瑞世","multiChoose":true,"shortName":"欧瑞世"},{"brandId":11641,"brandName":"AVIREX","multiChoose":true,"shortName":"AVIREX"},{"brandId":14102,"brandName":"MARA","multiChoose":true,"shortName":"MARA"},{"brandId":11049,"brandName":"UNIFLAME","multiChoose":true,"shortName":"UNIFLAME"},{"brandId":11054,"brandName":"PONTAPES","multiChoose":true,"shortName":"PONTAPES"},{"brandId":13763,"brandName":"Lukka Lux","multiChoose":true,"shortName":"Lukka Lux"},{"brandId":2859,"brandName":"史丹利","multiChoose":true,"shortName":"史丹利"},{"brandId":8249,"brandName":"SKINS","multiChoose":true,"shortName":"SKINS"},{"brandId":9210,"brandName":"Red Wing","multiChoose":true,"shortName":"Red Wing"},{"brandId":4083,"brandName":"赞贝拉","multiChoose":true,"shortName":"赞贝拉"},{"brandId":4451,"brandName":"壳牌","multiChoose":true,"shortName":"壳牌"},{"brandId":4804,"brandName":"Compressport","multiChoose":true,"shortName":"Compressport"},{"brandId":6458,"brandName":"MoonStar 月星","multiChoose":true,"shortName":"MoonStar 月星"},{"brandId":7820,"brandName":"冰熊","multiChoose":true,"shortName":"冰熊"},{"brandId":9784,"brandName":"普若卫斯","multiChoose":true,"shortName":"普若卫斯"},{"brandId":10543,"brandName":"JUST BOOM","multiChoose":true,"shortName":"JUST BOOM"},{"brandId":3207,"brandName":"嘉实多","multiChoose":true,"shortName":"嘉实多"},{"brandId":3654,"brandName":"哈瓦那","multiChoose":true,"shortName":"哈瓦那"},{"brandId":3832,"brandName":"卡骆驰","multiChoose":true,"shortName":"卡骆驰"},{"brandId":4849,"brandName":"惠普","multiChoose":true,"shortName":"惠普"},{"brandId":4948,"brandName":"Dare 2b","multiChoose":true,"shortName":"Dare 2b"},{"brandId":11047,"brandName":"snow peak","multiChoose":true,"shortName":"snow peak"},{"brandId":11052,"brandName":"icepardal","multiChoose":true,"shortName":"icepardal"},{"brandId":13463,"brandName":"维斯塔","multiChoose":true,"shortName":"维斯塔"},{"brandId":15329,"brandName":"Ucon ","multiChoose":true,"shortName":"Ucon "},{"brandId":3350,"brandName":"索康尼","multiChoose":true,"shortName":"索康尼"},{"brandId":4452,"brandName":"美孚","multiChoose":true,"shortName":"美孚"},{"brandId":4947,"brandName":"REGATTA","multiChoose":true,"shortName":"REGATTA"},{"brandId":6461,"brandName":"shockabsorber 瑷玻尔","multiChoose":true,"shortName":"shockabsorber 瑷玻尔"},{"brandId":6752,"brandName":"ROOTOTE","multiChoose":true,"shortName":"ROOTOTE"},{"brandId":8114,"brandName":"SPECIAL MAGIC","multiChoose":true,"shortName":"SPECIAL MAGIC"},{"brandId":9245,"brandName":"DACHSTEIN","multiChoose":true,"shortName":"DACHSTEIN"},{"brandId":9961,"brandName":"SSURPLUS","multiChoose":true,"shortName":"SSURPLUS"},{"brandId":10968,"brandName":"泰普森","multiChoose":true,"shortName":"泰普森"},{"brandId":4294,"brandName":"CRISPI","multiChoose":true,"shortName":"CRISPI"},{"brandId":7032,"brandName":"TEVA 太哇","multiChoose":true,"shortName":"TEVA 太哇"},{"brandId":7092,"brandName":"RIVIERAS ","multiChoose":true,"shortName":"RIVIERAS "},{"brandId":8096,"brandName":"JULBO","multiChoose":true,"shortName":"JULBO"},{"brandId":8159,"brandName":"Volley","multiChoose":true,"shortName":"Volley"},{"brandId":8301,"brandName":"悍将","multiChoose":true,"shortName":"悍将"},{"brandId":10145,"brandName":"瑜梵","multiChoose":true,"shortName":"瑜梵"},{"brandId":11053,"brandName":"namelessage","multiChoose":true,"shortName":"namelessage"},{"brandId":14556,"brandName":"MILLET 觅乐","multiChoose":true,"shortName":"MILLET 觅乐"},{"brandId":15200,"brandName":"Napapijri","multiChoose":true,"shortName":"Napapijri"},{"brandId":16090,"brandName":"JOMA","multiChoose":true,"shortName":"JOMA"},{"brandId":17670,"brandName":"Tully Lou","multiChoose":true,"shortName":"Tully Lou"},{"brandId":3831,"brandName":"勃肯","multiChoose":true,"shortName":"勃肯"},{"brandId":6968,"brandName":"LEKI","multiChoose":true,"shortName":"LEKI"},{"brandId":7600,"brandName":"法藤","multiChoose":true,"shortName":"法藤"},{"brandId":9666,"brandName":"SP-68","multiChoose":true,"shortName":"SP-68"},{"brandId":12619,"brandName":"Sunday Afternoons","multiChoose":true,"shortName":"Sunday Afternoons"},{"brandId":14785,"brandName":"朴途 PUTU","multiChoose":true,"shortName":"朴途 PUTU"},{"brandId":4738,"brandName":"迪奥多纳","multiChoose":true,"shortName":"迪奥多纳"},{"brandId":5473,"brandName":"HydraPak","multiChoose":true,"shortName":"HydraPak"},{"brandId":6138,"brandName":"SMARTWOOL","multiChoose":true,"shortName":"SMARTWOOL"},{"brandId":7902,"brandName":"RESPRO","multiChoose":true,"shortName":"RESPRO"},{"brandId":9215,"brandName":"ONZIE","multiChoose":true,"shortName":"ONZIE"},{"brandId":11055,"brandName":"purplecow","multiChoose":true,"shortName":"purplecow"},{"brandId":11424,"brandName":"Filson","multiChoose":true,"shortName":"Filson"},{"brandId":1552,"brandName":"UGG","multiChoose":true,"shortName":"UGG"},{"brandId":15682,"brandName":"MASKKING(MK)","multiChoose":true,"shortName":"MASKKING(MK)"},{"brandId":3650,"brandName":"宇崎日新","multiChoose":true,"shortName":"宇崎日新"},{"brandId":4576,"brandName":"Y-3","multiChoose":true,"shortName":"Y-3"},{"brandId":5622,"brandName":"INUK","multiChoose":true,"shortName":"INUK"},{"brandId":8631,"brandName":"JSC HOME","multiChoose":true,"shortName":"JSC HOME"},{"brandId":10567,"brandName":"酷仕客","multiChoose":true,"shortName":"酷仕客"},{"brandId":14895,"brandName":"Sip by swell","multiChoose":true,"shortName":"Sip by swell"},{"brandId":15098,"brandName":"法维诗","multiChoose":true,"shortName":"法维诗"},{"brandId":1983,"brandName":"拉夫·劳伦","multiChoose":true,"shortName":"拉夫·劳伦"},{"brandId":3933,"brandName":"奈爱","multiChoose":true,"shortName":"奈爱"},{"brandId":5416,"brandName":"泰尼卡","multiChoose":true,"shortName":"泰尼卡"},{"brandId":6449,"brandName":"Balega倍佳","multiChoose":true,"shortName":"Balega倍佳"},{"brandId":6683,"brandName":"Lululemon 露露柠檬","multiChoose":true,"shortName":"Lululemon 露露柠檬"},{"brandId":7036,"brandName":"BUTTERFLY","multiChoose":true,"shortName":"BUTTERFLY"},{"brandId":7050,"brandName":"SRIXON","multiChoose":true,"shortName":"SRIXON"},{"brandId":8024,"brandName":"ZHIK","multiChoose":true,"shortName":"ZHIK"},{"brandId":8320,"brandName":"alo yoga","multiChoose":true,"shortName":"alo yoga"},{"brandId":102036,"brandName":"TARRAMARRA","multiChoose":true,"shortName":"TARRAMARRA"},{"brandId":11542,"brandName":"just like A SPORT","multiChoose":true,"shortName":"just like A SPORT"},{"brandId":15242,"brandName":"Airscale智能体脂秤","multiChoose":true,"shortName":"Airscale智能体脂秤"},{"brandId":16540,"brandName":"suncao","multiChoose":true,"shortName":"suncao"},{"brandId":1950,"brandName":"哥特斯","multiChoose":true,"shortName":"哥特斯"},{"brandId":4084,"brandName":"佰适徒","multiChoose":true,"shortName":"佰适徒"},{"brandId":5436,"brandName":"宜乐","multiChoose":true,"shortName":"宜乐"},{"brandId":6353,"brandName":"Bauerfeind","multiChoose":true,"shortName":"Bauerfeind"},{"brandId":7047,"brandName":"PARADISO","multiChoose":true,"shortName":"PARADISO"},{"brandId":1167,"brandName":"GUESS","multiChoose":true,"shortName":"GUESS"},{"brandId":12739,"brandName":"格尔","multiChoose":true,"shortName":"格尔"},{"brandId":14740,"brandName":"ELALIBER","multiChoose":true,"shortName":"ELALIBER"},{"brandId":15145,"brandName":"律动风","multiChoose":true,"shortName":"律动风"},{"brandId":15764,"brandName":"WALL TATTO泰途","multiChoose":true,"shortName":"WALL TATTO泰途"},{"brandId":15931,"brandName":"EDGII","multiChoose":true,"shortName":"EDGII"},{"brandId":17676,"brandName":"ibody","multiChoose":true,"shortName":"ibody"},{"brandId":2108,"brandName":"蜚比","multiChoose":true,"shortName":"蜚比"},{"brandId":2985,"brandName":"小米","multiChoose":true,"shortName":"小米"},{"brandId":3649,"brandName":"达瓦","multiChoose":true,"shortName":"达瓦"},{"brandId":3935,"brandName":"蝴蝶","multiChoose":true,"shortName":"蝴蝶"},{"brandId":3963,"brandName":"休伯家","multiChoose":true,"shortName":"休伯家"},{"brandId":4575,"brandName":"鸭嘴兽","multiChoose":true,"shortName":"鸭嘴兽"},{"brandId":4862,"brandName":"乐格氏","multiChoose":true,"shortName":"乐格氏"},{"brandId":5151,"brandName":"Biolite","multiChoose":true,"shortName":"Biolite"},{"brandId":5152,"brandName":"GSI","multiChoose":true,"shortName":"GSI"},{"brandId":5154,"brandName":"REELIFE","multiChoose":true,"shortName":"REELIFE"},{"brandId":7093,"brandName":"Jox Sox","multiChoose":true,"shortName":"Jox Sox"},{"brandId":8025,"brandName":"MUSTO","multiChoose":true,"shortName":"MUSTO"},{"brandId":10962,"brandName":"Bopps","multiChoose":true,"shortName":"Bopps"},{"brandId":1123,"brandName":"科克兰","multiChoose":true,"shortName":"科克兰"},{"brandId":15361,"brandName":"乐步","multiChoose":true,"shortName":"乐步"},{"brandId":15574,"brandName":"Fiboard","multiChoose":true,"shortName":"Fiboard"},{"brandId":15666,"brandName":"kindlife","multiChoose":true,"shortName":"kindlife"},{"brandId":15780,"brandName":"SW","multiChoose":true,"shortName":"SW"},{"brandId":16754,"brandName":"CARBON ZERO","multiChoose":true,"shortName":"CARBON ZERO"},{"brandId":17682,"brandName":"SUNREX","multiChoose":true,"shortName":"SUNREX"},{"brandId":2636,"brandName":"来格仕","multiChoose":true,"shortName":"来格仕"},{"brandId":3211,"brandName":"EASTPAK","multiChoose":true,"shortName":"EASTPAK"},{"brandId":3651,"brandName":"专业海蓝","multiChoose":true,"shortName":"专业海蓝"},{"brandId":4453,"brandName":"道达尔","multiChoose":true,"shortName":"道达尔"},{"brandId":4484,"brandName":"STUSSY","multiChoose":true,"shortName":"STUSSY"},{"brandId":4867,"brandName":"MIMIMEMETE","multiChoose":true,"shortName":"MIMIMEMETE"},{"brandId":6136,"brandName":"LOWE ALPINE","multiChoose":true,"shortName":"LOWE ALPINE"},{"brandId":7037,"brandName":"邓禄普","multiChoose":true,"shortName":"邓禄普"},{"brandId":8619,"brandName":"Supreme","multiChoose":true,"shortName":"Supreme"},{"brandId":10601,"brandName":"Mini Cooper","multiChoose":true,"shortName":"Mini Cooper"},{"brandId":14006,"brandName":"carhartt","multiChoose":true,"shortName":"carhartt"},{"brandId":14099,"brandName":"瞩目者","multiChoose":true,"shortName":"瞩目者"},{"brandId":14923,"brandName":"大伟","multiChoose":true,"shortName":"大伟"},{"brandId":15380,"brandName":"VACYHOME","multiChoose":true,"shortName":"VACYHOME"},{"brandId":15647,"brandName":"浪骑士","multiChoose":true,"shortName":"浪骑士"},{"brandId":17059,"brandName":"Refuse to X","multiChoose":true,"shortName":"Refuse to X"},{"brandId":17661,"brandName":"Mobot","multiChoose":true,"shortName":"Mobot"},{"brandId":2857,"brandName":"TEETER","multiChoose":true,"shortName":"TEETER"},{"brandId":3934,"brandName":"巴克","multiChoose":true,"shortName":"巴克"},{"brandId":4127,"brandName":"TomTom","multiChoose":true,"shortName":"TomTom"},{"brandId":4233,"brandName":"科勒曼","multiChoose":true,"shortName":"科勒曼"},{"brandId":4610,"brandName":"百家适","multiChoose":true,"shortName":"百家适"},{"brandId":5288,"brandName":"锐可达","multiChoose":true,"shortName":"锐可达"},{"brandId":6923,"brandName":"Sweet Sweat 甜汗","multiChoose":true,"shortName":"Sweet Sweat 甜汗"},{"brandId":7040,"brandName":"GOSEN高神","multiChoose":true,"shortName":"GOSEN高神"},{"brandId":7041,"brandName":"HEAD海德","multiChoose":true,"shortName":"HEAD海德"},{"brandId":7046,"brandName":"NITTAKU","multiChoose":true,"shortName":"NITTAKU"},{"brandId":7054,"brandName":"捷多","multiChoose":true,"shortName":"捷多"},{"brandId":7057,"brandName":"HARUTA","multiChoose":true,"shortName":"HARUTA"},{"brandId":8029,"brandName":"康迪","multiChoose":true,"shortName":"康迪"},{"brandId":9412,"brandName":"快乐跑","multiChoose":true,"shortName":"快乐跑"}]